ImageTopoDec/__init__.py
ImageTopoDec/barcode.py
ImageTopoDec/barplot.py
ImageTopoDec/bin_state.py
ImageTopoDec/libbarpy.pyi
ImageTopoDec/libbarpy.so
imagetopodec-1.0.6.dist-info/METADATA
imagetopodec-1.0.6.dist-info/WHEEL
imagetopodec-1.0.6.dist-info/top_level.txt
imagetopodec-1.0.6.dist-info/RECORD
imagetopodec-1.0.6.dist-info/licenses/LICENSE
